<?xml version="1.0" encoding="utf-8"?><toc><breadcrumbs><li><a href="d75eb659-6335-53f6-af7a-81814a21ab7f.htm">Docs</a></li><li><a href="d75eb659-6335-53f6-af7a-81814a21ab7f.htm">Generative<wbr />AI</a></li><li><a href="182d9976-84ab-532f-4c8e-56fd8951e14d.htm">Generative<wbr />AI.<wbr />Core</a></li></breadcrumbs><tocItems><li><a id="d924e802-5d57-4314-a3dc-f812caadc3f0" class="has-submenu" href="d924e802-5d57-4314-a3dc-f812caadc3f0.htm"><span data-tocFile="../toc/IDADA.xml" class="icon toggle" onclick="ToggleExpandCollapse(this); return false;"><i class="fa fa-angle-right"> </i></span>Api<wbr />Base</a><ul class="toc-menu is-hidden"> </ul></li><li><a id="836ed3e3-66d4-ec0f-458d-c6fbac5518db" class="has-submenu" href="836ed3e3-66d4-ec0f-458d-c6fbac5518db.htm"><span data-tocFile="../toc/IDBDA.xml" class="icon toggle" onclick="ToggleExpandCollapse(this); return false;"><i class="fa fa-angle-right"> </i></span>Auth<wbr />Tokens</a><ul class="toc-menu is-hidden"> </ul></li><li><a id="6d96e5b1-8741-1c13-be3f-9f1c1f76d443" class="has-submenu" href="6d96e5b1-8741-1c13-be3f-9f1c1f76d443.htm"><span data-tocFile="../toc/IDCDA.xml" class="icon toggle" onclick="ToggleExpandCollapse(this); return false;"><i class="fa fa-angle-right"> </i></span>Base<wbr />Params</a><ul class="toc-menu is-hidden"> </ul></li><li><a id="26f0c087-3cd7-6a51-9c8a-1298a015719f" class="has-submenu" href="26f0c087-3cd7-6a51-9c8a-1298a015719f.htm"><span data-tocFile="../toc/IDDDA.xml" class="icon toggle" onclick="ToggleExpandCollapse(this); return false;"><i class="fa fa-angle-right"> </i></span>Client<wbr />Secrets</a><ul class="toc-menu is-hidden"> </ul></li><li><a id="17a6145c-2def-34d7-1ba8-4864ece51725" class="has-submenu" href="17a6145c-2def-34d7-1ba8-4864ece51725.htm"><span data-tocFile="../toc/IDEDA.xml" class="icon toggle" onclick="ToggleExpandCollapse(this); return false;"><i class="fa fa-angle-right"> </i></span>Code<wbr />Block</a><ul class="toc-menu is-hidden"> </ul></li><li><a id="f3157308-0935-11db-3629-47f0983c8e3c" class="has-submenu" href="f3157308-0935-11db-3629-47f0983c8e3c.htm"><span data-tocFile="../toc/IDFDA.xml" class="icon toggle" onclick="ToggleExpandCollapse(this); return false;"><i class="fa fa-angle-right"> </i></span>Credential<wbr />Configuration</a><ul class="toc-menu is-hidden"> </ul></li><li><a id="14f8f7d4-8d63-af1c-2b4e-79ea6d0255c7" class="has-submenu" href="14f8f7d4-8d63-af1c-2b4e-79ea6d0255c7.htm"><span data-tocFile="../toc/IDGDA.xml" class="icon toggle" onclick="ToggleExpandCollapse(this); return false;"><i class="fa fa-angle-right"> </i></span>File<wbr />Validator</a><ul class="toc-menu is-hidden"> </ul></li><li><a id="ee3c5b24-acd1-fdf3-fb55-85f3e870708e" class="has-submenu" href="ee3c5b24-acd1-fdf3-fb55-85f3e870708e.htm"><span data-tocFile="../toc/IDHDA.xml" class="icon toggle" onclick="ToggleExpandCollapse(this); return false;"><i class="fa fa-angle-right"> </i></span>Function<wbr />Calling<wbr />Behaviour</a><ul class="toc-menu is-hidden"> </ul></li><li><a id="3deab3bd-bd1b-1b99-f507-6e0a1a94575e" class="has-submenu" href="3deab3bd-bd1b-1b99-f507-6e0a1a94575e.htm"><span data-tocFile="../toc/IDIDA.xml" class="icon toggle" onclick="ToggleExpandCollapse(this); return false;"><i class="fa fa-angle-right"> </i></span>ICredentials</a><ul class="toc-menu is-hidden"> </ul></li><li><a id="dcf3a725-0537-5b10-48bc-25d47235d705" class="has-submenu" href="dcf3a725-0537-5b10-48bc-25d47235d705.htm"><span data-tocFile="../toc/IDJDA.xml" class="icon toggle" onclick="ToggleExpandCollapse(this); return false;"><i class="fa fa-angle-right"> </i></span>IFunction<wbr />Tool</a><ul class="toc-menu is-hidden"> </ul></li><li><a id="46aeb538-5c63-ca7e-fe3f-163f5b09e0ef" href="46aeb538-5c63-ca7e-fe3f-163f5b09e0ef.htm">IGenerative<wbr />Model</a></li><li><a id="711c413c-2750-6818-1a89-0b3c52b44635" class="has-submenu" href="711c413c-2750-6818-1a89-0b3c52b44635.htm"><span data-tocFile="../toc/IDLDA.xml" class="icon toggle" onclick="ToggleExpandCollapse(this); return false;"><i class="fa fa-angle-right"> </i></span>IGoogle<wbr />Authenticator</a><ul class="toc-menu is-hidden"> </ul></li><li><a id="ea15fd32-9b78-7c6f-393a-dac876ef4aeb" class="has-submenu" href="ea15fd32-9b78-7c6f-393a-dac876ef4aeb.htm"><span data-tocFile="../toc/IDMDA.xml" class="icon toggle" onclick="ToggleExpandCollapse(this); return false;"><i class="fa fa-angle-right"> </i></span>IPlatform<wbr />Adapter</a><ul class="toc-menu is-hidden"> </ul></li><li><a id="c77a8da1-ed62-a410-c0b9-3f8dec4ebb11" class="has-submenu" href="c77a8da1-ed62-a410-c0b9-3f8dec4ebb11.htm"><span data-tocFile="../toc/IDNDA.xml" class="icon toggle" onclick="ToggleExpandCollapse(this); return false;"><i class="fa fa-angle-right"> </i></span>Json<wbr />Block</a><ul class="toc-menu is-hidden"> </ul></li><li><a id="130615e8-3ce1-2c1f-b0be-6a00808b6755" class="has-submenu" href="130615e8-3ce1-2c1f-b0be-6a00808b6755.htm"><span data-tocFile="../toc/IDODA.xml" class="icon toggle" onclick="ToggleExpandCollapse(this); return false;"><i class="fa fa-angle-right"> </i></span>Mime<wbr />Type<wbr />Map</a><ul class="toc-menu is-hidden"> </ul></li><li><a id="5a3384b7-fe48-1528-2bf2-fb2d8284be3b" class="has-submenu" href="5a3384b7-fe48-1528-2bf2-fb2d8284be3b.htm"><span data-tocFile="../toc/IDPDA.xml" class="icon toggle" onclick="ToggleExpandCollapse(this); return false;"><i class="fa fa-angle-right"> </i></span>Model<wbr />Params</a><ul class="toc-menu is-hidden"> </ul></li><li><a id="bd95ab9f-d020-fa44-8b02-9a1d55384050" class="has-submenu" href="bd95ab9f-d020-fa44-8b02-9a1d55384050.htm"><span data-tocFile="../toc/IDQDA.xml" class="icon toggle" onclick="ToggleExpandCollapse(this); return false;"><i class="fa fa-angle-right"> </i></span>Progress<wbr />Stream<wbr />Content</a><ul class="toc-menu is-hidden"> </ul></li><li><a id="0a0137b9-fe9d-9d03-87a9-0543989614dc" class="has-submenu" href="0a0137b9-fe9d-9d03-87a9-0543989614dc.htm"><span data-tocFile="../toc/IDRDA.xml" class="icon toggle" onclick="ToggleExpandCollapse(this); return false;"><i class="fa fa-angle-right"> </i></span>Request<wbr />Url</a><ul class="toc-menu is-hidden"> </ul></li></tocItems></toc>